README.md
setup.py
orange3_shap.egg-info/PKG-INFO
orange3_shap.egg-info/SOURCES.txt
orange3_shap.egg-info/dependency_links.txt
orange3_shap.egg-info/entry_points.txt
orange3_shap.egg-info/namespace_packages.txt
orange3_shap.egg-info/not-zip-safe
orange3_shap.egg-info/requires.txt
orange3_shap.egg-info/top_level.txt
orangecontrib/__init__.py
orangecontrib/oshap/__init__.py
orangecontrib/oshap/tests/__init__.py
orangecontrib/oshap/tests/test_shap_single.py
orangecontrib/oshap/tests/test_shap_summary.py
orangecontrib/oshap/widgets/OWShapSingle.py
orangecontrib/oshap/widgets/OWShapSummary.py
orangecontrib/oshap/widgets/__init__.py
orangecontrib/oshap/widgets/icons/Shap.png
orangecontrib/oshap/widgets/icons/shap_single.png
orangecontrib/oshap/widgets/icons/shap_summary.png