Metadata-Version: 1.1
Name: orange3-shap
Version: 0.0.4
Summary: Orange3 add-on for exploring shap values.
Home-page: https://github.com/jpoullet2000/orange3-shap
Author: Jean-Baptiste Poullet
Author-email: jeanbaptistepoullet@gsk.com
License: CC-BY-NC-3.0
Keywords: shap,orange3 add-on
Platform: UNKNOWN
Classifier: Development Status :: 4 - Beta
Classifier: Environment :: X11 Applications :: Qt
Classifier: Environment :: Plugins
Classifier: Programming Language :: Python
Classifier: License :: Other/Proprietary License
Classifier: Operating System :: OS Independent
Classifier: Topic :: Scientific/Engineering :: Artificial Intelligence
Classifier: Topic :: Scientific/Engineering :: Visualization
Classifier: Topic :: Software Development :: Libraries :: Python Modules
Classifier: Intended Audience :: Education
Classifier: Intended Audience :: Science/Research
Classifier: Intended Audience :: Developers
